{
  "$schema": "https://json.openmrs.org/routes.schema.json",
  "backendDependencies": {
    "webservices.rest": "^2.24.0"
  },
  "pages": [
  ],
  "extensions": [
    {
      "name": "patient-hiv-status-tag",
      "slot": "patient-banner-tags-slot",
      "component": "patientHivStatusTag"
    },
    {
      "name": "hts-patient-encounters-list-ext",
      "slot": "hts-summary-dashboard-slot",
      "component": "htsPatientEncountersList"
    },
    {
      "name": "hts-service-summary-list-ext",
      "slot": "hiv-patient-summary-dashboard-slot",
      "component": "htsServiceSummaryList"
    },
    {
      "name": "hts-home-header-ext",
      "slot": "hts-home-header-slot",
      "component": "htsHomeHeader"
    },
    {
      "name": "hts-home-tile-ext",
      "slot": "hts-home-tile-slot",
      "component": "htsHomeTiles"
    },
    {
      "name": "hts-home-tabs-ext",
      "slot": "hts-home-tabs-slot",
      "component": "htsHomeTabs"
    },
    {
      "name": "ct-home-header-ext",
      "slot": "ct-home-header-slot",
      "component": "ctHomeHeader"
    },
    {
      "name": "ct-home-tile-ext",
      "slot": "ct-home-tile-slot",
      "component": "ctHomeTiles"
    },
    {
      "name": "ct-home-tabs-ext",
      "slot": "ct-home-tabs-slot",
      "component": "ctHomeTabs"
    },
    {
      "name": "hiv-care-and-treatment-dashboard-link",
      "slot": "dashboard-slot",
      "component": "hivCareAndTreatmentFolderLink"
    },
    {
      "name": "care-and-treatment-dashboard-ext",
      "slot": "ohri-hiv-care-and-treatment-dashboard-slot",
      "component": "hivCareAndTreatmentDashboardLink"
    },
    {
      "name": "ohri-care-and-treatment-dashboard",
      "slot": "care-and-treatment-dashboard-slot",
      "component": "hivCareAndTreatmentDashboard",
      "meta": {
        "name": "care-and-treatment",
        "slot": "care-and-treatment-dashboard-slot",
        "config": { "columns": 1, "type": "grid", "programme": "ct", "dashboardTitle": "C&T Home Page" },
        "title": "Care and Treatment"
      }
    },
    {
      "name": "hiv-prevention-dashboard-link",
      "slot": "dashboard-slot",
      "component": "hivPreventionFolderLink"
    },
    {
      "name": "ohri-hiv-prevention-dashboard-ext",
      "slot": "ohri-hiv-prevention-dashboard-slot",
      "component": "hivPreventionDashboardLink"
    },
    {
      "name": "ohri-hiv-prevention-dashboard",
      "slot": "hts-dashboard-slot",
      "component": "hivPreventionDashboard",
      "meta": {
        "name": "hts",
        "slot": "hts-dashboard-slot",
        "config": { "columns": 1, "type": "grid", "programme": "hts", "dashboardTitle": "HTS Home Page" },
        "title": "HIV Testing Services"
      }
    },
    {
      "name": "lab-results-home-header-ext",
      "slot": "lab-results-home-header-slot",
      "component": "labResultsHomeHeader"
    },
    {
      "name": "lab-results-home-tile-ext",
      "slot": "lab-results-home-tile-slot",
      "component": "labResultsHomeTiles"
    },
    {
      "name": "lab-results-tabs-ext",
      "slot": "lab-results-home-tabs-slot",
      "component": "labResultsHomeTabs"
    }

  ]
}
